[{"id":"female","enabled":true,"icon":"♀","description":"Feminine identity","name":"Female","image":"genders/female.png"},{"id":"hermaphrodite","enabled":true,"icon":"⚥","description":"Both masculine and feminine characteristics","image":"genders/hermaphrodite.png","name":"Hermaphrodite"},{"id":"male","icon":"♂","enabled":true,"image":"genders/male.png","name":"Male","description":"Masculine identity"},{"id":"nonbinary","description":"Identity outside the gender binary","name":"Non-Binary","image":"genders/nonbinary.png","enabled":true,"icon":"⚪"},{"id":"other","description":"Custom or unspecified identity","name":"Other","image":"genders/other.png","enabled":true,"icon":"✧"},{"id":"transgender","enabled":true,"icon":"⚧","description":"Gender differs from birth assignment","image":"genders/transgender.png","name":"Transgender"}]
