[{"id":"female","image":"genders/female.png","icon":"♀","description":"Feminine identity","enabled":true,"name":"Female"},{"id":"hermaphrodite","enabled":true,"name":"Hermaphrodite","image":"genders/hermaphrodite.png","icon":"⚥","description":"Both masculine and feminine characteristics"},{"id":"male","description":"Masculine identity","icon":"♂","image":"genders/male.png","name":"Male","enabled":true},{"id":"nonbinary","image":"genders/nonbinary.png","icon":"⚪","description":"Identity outside the gender binary","name":"Non-Binary","enabled":true},{"id":"other","icon":"✧","description":"Custom or unspecified identity","image":"genders/other.png","name":"Other","enabled":true},{"id":"transgender","icon":"⚧","description":"Gender differs from birth assignment","image":"genders/transgender.png","enabled":true,"name":"Transgender"}]
