[{"id":"alkaalon","stat_maximums":{"athletics":7,"endurance":7},"free_advances":[],"description":"Graceful and long-lived. Masters of magic and archery.","enabled":true,"icon":"🧝","prerequisites":[],"mana":120,"created_at":"2026-05-15T22:39:12.401Z","stamina":90,"image":"species/alkaalon.png","health":80,"name":"Alka Alon","base_stats":{"awareness":3,"marksmanship":3,"agility":3},"updated_at":"2026-05-15T22:39:12.401Z","stat_minimums":{"awareness":3,"agility":3}},{"id":"dradrien","stat_minimums":{"endurance":3,"crafting":3},"base_stats":{"crafting":3,"athletics":3,"endurance":4},"updated_at":"2026-05-15T22:41:14.945Z","name":"Alon Dradrien","health":130,"image":"species/dradrien.png","created_at":"2026-05-15T22:41:14.945Z","stamina":120,"mana":30,"enabled":true,"icon":"⛏️","prerequisites":[],"description":"Stout and resilient craftsmen. Masters of stone and steel.","free_advances":[],"stat_maximums":{"stealth":6,"agility":6}},{"id":"angel","free_advances":[],"starting_xp":5000,"description":"One of the celestials, winged guardian of life","stat_maximums":{},"mana":50,"created_at":"2026-06-30T03:09:22.313Z","stamina":100,"icon":"","enabled":true,"prerequisites":[],"name":"Angel","health":100,"image":"species/angel.png","stat_minimums":{},"base_stats":{},"updated_at":"2026-06-30T03:09:22.313Z"},{"id":"anthromorph","prerequisites":[],"enabled":true,"icon":"","mana":50,"created_at":"2026-06-30T03:10:18.141Z","stamina":100,"stat_maximums":{},"free_advances":[],"description":"Various anthropomorphic beings.","starting_xp":5000,"base_stats":{},"updated_at":"2026-06-30T03:10:18.141Z","stat_minimums":{},"image":"species/anthromorph.png","name":"Anthromorph","health":100},{"id":"beastfolk","enabled":true,"icon":"","prerequisites":[],"mana":50,"stamina":100,"created_at":"2026-06-30T03:11:22.991Z","stat_maximums":{},"free_advances":[],"starting_xp":5000,"description":"Sentient small animals with the ability to speak and interact.","base_stats":{},"updated_at":"2026-06-30T03:11:22.991Z","stat_minimums":{},"image":"species/beastfolk.png","health":100,"name":"Beastfolk"},{"id":"demon","base_stats":{"fighting":4,"endurance":3,"will":4},"updated_at":"2026-07-08T14:37:49.139Z","stat_minimums":{"will":4,"endurance":3},"image":"species/demon.png","name":"Demon","health":"150","prerequisites":[],"icon":"👹","enabled":true,"stamina":"120","mana":"100","stat_maximums":{"healing":4,"wisdom":5},"starting_xp":"7000","description":"Creatures of the abyss. Powerful but feared.","free_advances":[]},{"id":"dragonborn","stamina":"100","mana":"80","prerequisites":[],"icon":"🐉","enabled":true,"description":"Proud dragon-blooded warriors with breath weapons.","starting_xp":"6000","free_advances":[],"stat_maximums":{"stealth":5,"thievery":5},"stat_minimums":{"endurance":3,"will":3},"base_stats":{"fighting":3,"will":3,"endurance":3},"updated_at":"2026-07-08T14:37:49.234Z","health":"120","name":"Dragonborn","image":"species/dragonborn.png"},{"id":"drow","mana":"100","stamina":"85","prerequisites":[],"icon":"🌑","enabled":true,"free_advances":[],"starting_xp":"6800","description":"Dark elves from the underdark. Masters of shadow.","stat_maximums":{"healing":5},"stat_minimums":{"stealth":3,"awareness":3},"base_stats":{"stealth":4,"awareness":3,"deception":3},"updated_at":"2026-07-08T14:37:49.362Z","health":"75","name":"Drow","image":"species/drow.png"},{"id":"dwarf","stat_maximums":{"agility":6,"stealth":6},"starting_xp":"7200","description":"Stout and resilient craftsmen. Masters of stone and steel.","free_advances":[],"prerequisites":[],"icon":"⛏️","enabled":true,"stamina":"120","mana":"30","image":"species/dwarf.png","health":"130","name":"Dwarf","base_stats":{"endurance":4,"athletics":3,"crafting":3},"updated_at":"2026-07-08T14:37:49.485Z","stat_minimums":{"endurance":3,"crafting":3}},{"id":"elf","stat_minimums":{"agility":3,"awareness":3},"base_stats":{"awareness":3,"marksmanship":3,"agility":3},"updated_at":"2026-07-08T14:37:49.567Z","health":"80","name":"Elf","image":"species/elf.png","mana":"120","stamina":"90","icon":"🧝","enabled":true,"prerequisites":[],"free_advances":[],"description":"Graceful and long-lived. Masters of magic and archery.","starting_xp":"9000","stat_maximums":{"endurance":7,"athletics":7}},{"id":"enshadowed","free_advances":[],"description":"Renegade Alka Alon who are aligned with Korbol the Necromancer","starting_xp":6500,"stat_maximums":{},"mana":50,"stamina":100,"created_at":"2026-06-30T03:13:28.607Z","icon":"","enabled":true,"prerequisites":[],"name":"Enshadowed","health":100,"image":"species/enshadowed.png","stat_minimums":{},"base_stats":{},"updated_at":"2026-06-30T03:13:28.607Z"},{"id":"fae","health":40,"name":"Fae","image":"species/fae.png","stat_minimums":{"agility":4},"updated_at":"2026-06-02T02:11:53.464Z","base_stats":{"entertaining":3,"will":3,"agility":4},"free_advances":[],"description":"The Fae are creatures of raw magic, emotion, and nature, originating from a realm where physical laws are secondary to whim and wonder. They are immortal or incredibly lon","stat_maximums":{"athletics":4,"fighting":4,"endurance":4},"mana":150,"created_at":"2026-06-02T02:11:53.464Z","stamina":70,"enabled":true,"icon":"🧚","prerequisites":[]},{"id":"fairy","health":"40","name":"Fairy","image":"species/fairy.png","stat_minimums":{"agility":4},"base_stats":{"entertaining":3,"will":3,"agility":4},"updated_at":"2026-07-08T14:37:49.863Z","free_advances":[],"starting_xp":"7300","description":"Tiny magical beings with wings. Masters of enchantment.","stat_maximums":{"athletics":4,"fighting":4,"endurance":4},"mana":"150","stamina":"70","icon":"🧚","enabled":true,"prerequisites":[]},{"id":"githyanki","image":"species/githyanki.png","name":"Githyanki","health":100,"base_stats":{},"updated_at":"2026-06-30T03:12:09.402Z","stat_minimums":{},"stat_maximums":{},"free_advances":[],"starting_xp":10000,"description":"","prerequisites":[],"icon":"","enabled":true,"mana":50,"stamina":100,"created_at":"2026-06-30T03:12:09.402Z"},{"id":"gnome","base_stats":{"intelligence":4,"crafting":3,"deception":3},"updated_at":"2026-07-08T14:37:50.074Z","stat_minimums":{"intelligence":3,"crafting":2},"image":"species/gnome.png","name":"Gnome","health":"60","prerequisites":[],"icon":"🔧","enabled":true,"stamina":"80","mana":"100","stat_maximums":{"endurance":6,"fighting":5},"starting_xp":"5500","description":"Clever and inventive. Masters of illusion and tinkering.","free_advances":[]},{"id":"goblin","starting_xp":"8000","description":"Small green-skinned creatures. Cunning survivors.","free_advances":[],"stat_maximums":{"influence":5,"persuasion":4},"stamina":"95","mana":"50","icon":"👺","enabled":true,"prerequisites":[],"name":"Goblin","health":"65","image":"species/goblin.png","stat_minimums":{"stealth":2,"thievery":2},"base_stats":{"stealth":3,"survival":3,"thievery":3},"updated_at":"2026-07-08T14:37:50.199Z"},{"id":"gurvani","health":65,"name":"Gurvani","image":"species/gurvani.png","stat_minimums":{"thievery":2,"stealth":2},"base_stats":{"thievery":3,"stealth":3,"survival":3},"updated_at":"2026-05-15T22:39:37.163Z","description":"Small green-skinned creatures. Cunning survivors.","free_advances":[],"stat_maximums":{"influence":5,"persuasion":4},"stamina":95,"created_at":"2026-05-15T22:39:37.163Z","mana":50,"prerequisites":[],"enabled":true,"icon":"👺"},{"id":"half-elf","base_stats":{"awareness":3,"persuasion":3},"updated_at":"2026-07-08T14:37:50.436Z","stat_minimums":{"awareness":2},"image":"species/half-elf.png","name":"Half-Elf","health":"90","icon":"🌙","enabled":true,"prerequisites":[],"mana":"80","stamina":"95","stat_maximums":{},"free_advances":[],"starting_xp":"10000","description":"Blending human adaptability with elven grace."},{"id":"half-orc","image":"species/half-orc.png","name":"Half-Orc","health":"140","base_stats":{"endurance":3,"fighting":3,"athletics":4},"updated_at":"2026-07-08T14:37:50.542Z","stat_minimums":{"athletics":3,"endurance":3},"stat_maximums":{"intelligence":6,"persuasion":5},"free_advances":[],"description":"Strong and fierce. Warriors with orcish blood.","starting_xp":"6000","enabled":true,"icon":"💪","prerequisites":[],"mana":"20","stamina":"130"},{"id":"halfling","mana":"60","stamina":"110","prerequisites":[],"enabled":true,"icon":"🍀","free_advances":[],"description":"Small but lucky. Known for their stealth and charm.","starting_xp":"8000","stat_maximums":{"fighting":6,"athletics":6},"stat_minimums":{"stealth":3,"thievery":2},"base_stats":{"stealth":3,"thievery":3,"persuasion":3},"updated_at":"2026-07-08T14:37:50.662Z","name":"Halfling","health":"70","image":"species/halfling.png"},{"id":"hulka","image":"species/hulka.png","name":"Hulka Alon","health":130,"base_stats":{"awareness":3,"endurance":3,"survival":4},"updated_at":"2026-05-15T22:42:35.851Z","stat_minimums":{"endurance":3,"survival":3},"stat_maximums":{"crafting":5,"intelligence":6},"free_advances":[],"description":"Cursed shapeshifters. Fierce when transformed.","prerequisites":[],"icon":"🐺","enabled":true,"mana":30,"stamina":140,"created_at":"2026-05-15T22:42:35.851Z"},{"id":"human","image":"species/human.png","health":"100","name":"Human","base_stats":{},"updated_at":"2026-07-08T14:37:50.884Z","stat_minimums":{},"stat_maximums":{},"starting_xp":"10000","description":"Versatile and adaptable. The most common race in the realm.","free_advances":[],"icon":"👤","enabled":true,"prerequisites":[],"stamina":"100","mana":"50"},{"id":"hyosube","image":"species/hyosube.png","health":100,"name":"Hyosube","base_stats":{},"updated_at":"2026-06-30T03:15:41.986Z","stat_minimums":{},"stat_maximums":{},"free_advances":[],"starting_xp":0,"description":"Mischevious small furry yokai, known to steal eggplants and live in undeground burrows near streams.","icon":"","enabled":true,"prerequisites":[],"mana":50,"stamina":100,"created_at":"2026-06-30T03:15:41.986Z"},{"id":"imp","mana":"90","stamina":"100","enabled":true,"icon":"👿","prerequisites":[],"free_advances":[],"starting_xp":"4000","description":"Small mischievous devils. Cunning tricksters.","stat_maximums":{"fighting":5,"athletics":5},"stat_minimums":{"agility":3,"deception":3},"base_stats":{"agility":4,"thievery":3,"deception":4},"updated_at":"2026-07-08T14:37:51.107Z","health":"50","name":"Imp","image":"species/imp.png"},{"id":"kappa","stat_minimums":{},"base_stats":{},"updated_at":"2026-06-30T03:16:51.692Z","name":"Kappa","health":100,"image":"species/kappa.png","created_at":"2026-06-30T03:16:51.692Z","stamina":100,"mana":50,"enabled":true,"icon":"","prerequisites":[],"description":"A type of water spirit yokai","starting_xp":0,"free_advances":[],"stat_maximums":{}},{"id":"karasutengu","updated_at":"2026-06-30T03:17:34.657Z","base_stats":{},"stat_minimums":{},"image":"species/karasutengu.png","name":"Karasu-Tengu","health":100,"enabled":true,"icon":"","prerequisites":[],"stamina":100,"created_at":"2026-06-30T03:17:34.657Z","mana":50,"stat_maximums":{},"starting_xp":0,"description":"Avian type of yokai","free_advances":[]},{"id":"karshak","stat_minimums":{"crafting":3,"endurance":3},"updated_at":"2026-05-15T22:40:22.791Z","base_stats":{"endurance":4,"crafting":3,"athletics":3},"name":"Karshak Alon","health":130,"image":"species/karshak.png","stamina":120,"created_at":"2026-05-15T22:40:22.791Z","mana":30,"prerequisites":[],"enabled":true,"icon":"⛏️","description":"Stout and resilient craftsmen. Masters of stone and steel.","free_advances":[],"stat_maximums":{"agility":6,"stealth":6}},{"id":"kitsune","name":"Kitsune","health":100,"image":"species/kitsune.png","stat_minimums":{},"base_stats":{},"updated_at":"2026-06-30T03:18:24.815Z","starting_xp":0,"description":"A special type of fox spirit yokai","free_advances":[],"stat_maximums":{},"stamina":100,"created_at":"2026-06-30T03:18:24.815Z","mana":50,"icon":"","enabled":true,"prerequisites":[]},{"id":"malkas","image":"species/malkas.png","health":130,"name":"Malkas Alon","base_stats":{"crafting":3,"athletics":3,"endurance":4},"updated_at":"2026-05-15T22:40:42.973Z","stat_minimums":{"endurance":3,"crafting":3},"stat_maximums":{"stealth":6,"agility":6},"description":"Stout and resilient craftsmen. Masters of stone and steel.","free_advances":[],"prerequisites":[],"enabled":true,"icon":"⛏️","stamina":120,"created_at":"2026-05-15T22:40:42.973Z","mana":30},{"id":"merfolk","name":"Merfolk","health":"90","image":"species/merfolk.png","stat_minimums":{"athletics":3},"base_stats":{"awareness":3,"athletics":4,"survival":3},"updated_at":"2026-07-08T14:37:51.686Z","starting_xp":"4000","description":"Aquatic beings of the deep. Masters of the sea.","free_advances":[],"stat_maximums":{"crafting":5},"stamina":"120","mana":"80","icon":"🧜","enabled":true,"prerequisites":[]},{"id":"metsakinsa","enabled":true,"icon":"👹","prerequisites":[],"stamina":120,"created_at":"2026-05-15T22:43:39.309Z","mana":100,"stat_maximums":{"wisdom":5,"healing":4},"description":"Creatures of the abyss. Powerful but feared.","free_advances":[],"updated_at":"2026-05-15T22:43:39.309Z","base_stats":{"fighting":4,"will":4,"endurance":3},"stat_minimums":{"will":4,"endurance":3},"image":"species/metsakinsa.png","health":150,"name":"Met Sakinsa"},{"id":"minotaur","description":"Bull-headed warriors. Powerful and relentless.","starting_xp":"4000","free_advances":[],"stat_maximums":{"intelligence":5,"thievery":4,"stealth":4},"stamina":"140","mana":"20","enabled":true,"icon":"🐂","prerequisites":[],"name":"Minotaur","health":"160","image":"species/minotaur.png","stat_minimums":{"athletics":4,"endurance":3},"updated_at":"2026-07-08T14:37:52.040Z","base_stats":{"fighting":3,"endurance":4,"athletics":5}},{"id":"nekomata","name":"Nekomata","health":100,"image":"species/nekomata.png","stat_minimums":{},"base_stats":{},"updated_at":"2026-06-30T03:18:55.963Z","free_advances":[],"description":"A form of feline yokai","starting_xp":0,"stat_maximums":{},"mana":50,"stamina":100,"created_at":"2026-06-30T03:18:55.963Z","enabled":true,"icon":"","prerequisites":[]},{"id":"nemovorti","image":"species/nemovorti.png","health":100,"name":"Nemovorti","base_stats":{},"updated_at":"2026-06-30T03:19:59.257Z","stat_minimums":{},"stat_maximums":{},"starting_xp":0,"description":"Undead spirits of enchadowed Alka Alon who use necromancy to move into the host body of another being","free_advances":[],"enabled":true,"icon":"","prerequisites":[],"stamina":100,"created_at":"2026-06-30T03:19:59.257Z","mana":50},{"id":"ningen","stat_maximums":{},"description":"Versatile and adaptable. The most common race in the realm.","free_advances":[],"prerequisites":[],"enabled":true,"icon":"👤","stamina":100,"created_at":"2026-06-28T19:38:29.029Z","mana":50,"image":"species/ningen.png","name":"Ningen","health":100,"base_stats":{},"updated_at":"2026-06-28T19:38:29.029Z","stat_minimums":{}},{"id":"oni","stat_minimums":{},"base_stats":{},"updated_at":"2026-06-30T03:21:39.304Z","name":"Oni","health":100,"image":"species/oni.png","stamina":100,"created_at":"2026-06-30T03:21:39.304Z","mana":50,"icon":"","enabled":true,"prerequisites":[],"starting_xp":2500,"description":"Oni are a kind of demon or yokai in the Sengoku universe... most famous are the BLUE and RED oni.","free_advances":[],"stat_maximums":{}},{"id":"reptilian","name":"Reptilian","health":"110","image":"species/reptilian.png","stat_minimums":{"endurance":3,"awareness":2},"base_stats":{"awareness":3,"endurance":3,"survival":3},"updated_at":"2026-07-08T14:37:52.540Z","starting_xp":"4000","description":"Cold-blooded lizard folk. Ancient and patient.","free_advances":[],"stat_maximums":{"influence":5,"persuasion":5},"stamina":"100","mana":"60","icon":"🦎","enabled":true,"prerequisites":[]},{"id":"satyr","free_advances":[],"description":"Half-goat forest dwellers. Lovers of music and revelry.","starting_xp":"4000","stat_maximums":{},"mana":"70","stamina":"110","prerequisites":[],"enabled":true,"icon":"🎭","name":"Satyr","health":"95","image":"species/satyr.png","stat_minimums":{"entertaining":3,"agility":2},"updated_at":"2026-07-08T14:37:52.629Z","base_stats":{"agility":3,"persuasion":3,"entertaining":4}},{"id":"talalon","prerequisites":[],"enabled":true,"icon":"🍀","stamina":110,"created_at":"2026-05-15T22:38:28.345Z","mana":60,"stat_maximums":{"fighting":6,"athletics":6},"description":"Small but lucky. Known for their stealth and charm.","free_advances":[],"updated_at":"2026-05-15T22:38:28.345Z","base_stats":{"persuasion":3,"stealth":3,"thievery":3},"stat_minimums":{"thievery":2,"stealth":3},"image":"species/talalon.png","health":70,"name":"Tal Alon"},{"id":"teraalon","image":"species/teraalon.png","name":"Tera Alon","health":90,"base_stats":{"persuasion":3,"awareness":3},"updated_at":"2026-05-15T22:40:04.847Z","stat_minimums":{"awareness":2},"stat_maximums":{},"free_advances":[],"description":"Blending human adaptability with elven grace.","prerequisites":[],"enabled":true,"icon":"🌙","mana":80,"created_at":"2026-05-15T22:40:04.847Z","stamina":95},{"id":"tiefling","stat_minimums":{"will":3},"updated_at":"2026-07-08T14:37:52.917Z","base_stats":{"deception":3,"intelligence":3,"will":3},"name":"Tiefling","health":"90","image":"species/tiefling.png","stamina":"90","mana":"110","icon":"😈","enabled":true,"prerequisites":[],"description":"Touched by infernal heritage. Mistrusted but powerful.","starting_xp":"4000","free_advances":[],"stat_maximums":{"healing":6}},{"id":"tsuchigumo","base_stats":{},"updated_at":"2026-06-30T03:22:21.735Z","stat_minimums":{},"image":"species/tsuchigumo.png","name":"Tsuchigumo","health":100,"prerequisites":[],"icon":"","enabled":true,"mana":50,"stamina":100,"created_at":"2026-06-30T03:22:21.735Z","stat_maximums":{},"free_advances":[],"description":"Arachnid type yokai","starting_xp":3000},{"id":"vampire","stamina":"80","mana":"120","prerequisites":[],"icon":"🧛","enabled":true,"starting_xp":"4000","description":"Undead immortals. Powerful but vulnerable to sunlight.","free_advances":[],"stat_maximums":{"healing":3},"stat_minimums":{"influence":3,"will":3},"base_stats":{"will":3,"influence":4,"deception":3},"updated_at":"2026-07-08T14:37:53.088Z","name":"Vampire","health":"100","image":"species/vampire.png"},{"id":"werewolf","health":"130","name":"Werewolf","image":"species/werewolf.png","stat_minimums":{"endurance":3,"survival":3},"base_stats":{"awareness":3,"survival":4,"endurance":3},"updated_at":"2026-07-08T14:37:53.199Z","starting_xp":"4000","description":"Cursed shapeshifters. Fierce when transformed.","free_advances":[],"stat_maximums":{"intelligence":6,"crafting":5},"stamina":"140","mana":"30","prerequisites":[],"icon":"🐺","enabled":true},{"id":"yokai","stamina":120,"created_at":"2026-06-28T19:39:46.988Z","mana":100,"enabled":true,"icon":"👹","prerequisites":[],"description":"Creatures of the abyss. Powerful but feared.","free_advances":[],"stat_maximums":{"wisdom":5,"healing":4},"stat_minimums":{"endurance":3,"will":4},"updated_at":"2026-06-28T19:39:46.988Z","base_stats":{"fighting":2,"will":4,"endurance":3},"name":"Yokai","health":150,"image":"species/yokai.png"}]
